django_admin_recent_inlines/__init__.py
django_admin_recent_inlines/admin.py
django_admin_recent_inlines/apps.py
django_admin_recent_inlines/static/admin/js/viewall_inlines.js
django_admin_recent_inlines/templates/admin/edit_inline/recent_tabular.html
django_admin_recent_inlines-0.1.3.dist-info/LICENSE
django_admin_recent_inlines-0.1.3.dist-info/METADATA
django_admin_recent_inlines-0.1.3.dist-info/WHEEL
django_admin_recent_inlines-0.1.3.dist-info/RECORD
