Metadata-Version: 2.3
Name: django-admin-recent-inlines
Version: 0.1.3
Summary: Recent inlines with view-all functionality
License: MIT
Keywords: django,admin,inlines,recent
Author: Konrad Beck
Author-email: konrad.beck@merchantcapital.co.za
Requires-Python: >=3.11,<4.0
Classifier: License :: OSI Approved :: MIT License
Classifier: Programming Language :: Python :: 3
Classifier: Programming Language :: Python :: 3.11
Classifier: Programming Language :: Python :: 3.12
Classifier: Programming Language :: Python :: 3.13
Requires-Dist: Django (>=4.0)
Project-URL: Homepage, https://github.com/AugendLimited/django-admin-recent-inlines
Project-URL: Repository, https://github.com/AugendLimited/django-admin-recent-inlines
